{
	"name": "Car",
	"plugin-id": "Sprite",
	"sid": 817066553513305,
	"isGlobal": false,
	"instanceVariables": [],
	"behaviorTypes": [
		{
			"behaviorId": "solid",
			"name": "Solid",
			"sid": 759334423172715
		}
	],
	"effectTypes": [],
	"animations": {
		"items": [
			{
				"frames": [
					{
						"width": 350,
						"height": 188,
						"originX": 0.5906146844053216,
						"originY": 0.6157894736842106,
						"originalSource": "",
						"exportFormat": "png",
						"exportQuality": 0.8,
						"imageSpriteId": 3796780,
						"collisionPoly": {
							"points": [
								0.0988296488946684,
								0.07228915662650602,
								0.5156046814044213,
								0.04819277108433735,
								0.8530554724435603,
								0.20120494280793108,
								0.9817949826929806,
								0.7975904512213869,
								0.36475911434633557,
								0.8120480469750949,
								0.02990887703501039,
								0.6638553564743203
							]
						},
						"useCollisionPoly": true,
						"duration": 1
					}
				],
				"sid": 527968167552338,
				"name": "Animation 1",
				"isLooping": false,
				"isPingPong": false,
				"repeatCount": 1,
				"repeatTo": 0,
				"speed": 5
			}
		],
		"subfolders": []
	}
}